{
  "page": 1,
  "results": [
    {
      "adult": false,
      "backdrop_path": "/1x9e0qWonw634NhIsRdvnneeqvN.jpg",
      "genre_ids": [
        10749,
        18
      ],
      "id": 1523145,
      "original_language": "ru",
      "original_title": "Твоё сердце будет разбито",
      "overview": "",
      "popularity": 1201.7892,
      "poster_path": "/iGpMm603GUKH2SiXB2S5m4sZ17t.jpg",
      "release_date": "2026-03-26",
      "title": "Your Heart Will Be Broken",
      "video": false,
      "vote_average": 6.9,
      "vote_count": 35
    },
    {
      "adult": false,
      "backdrop_path": "/iN41Ccw4DctL8npfmYg1j5Tr1eb.jpg",
      "genre_ids": [
        878,
        12,
        14
      ],
      "id": 83533,
      "original_language": "en",
      "original_title": "Avatar: Fire and Ash",
      "overview": "Après la mort de Neteyam, Jake et Neytiri affrontent leur chagrin tout en faisant face au Peuple des Cendres, une tribu Na’vi redoutable menée par la fougueuse Varang, alors que le conflit sur Pandora s’intensifie et qu’une nouvelle quête morale s’amorce.",
      "popularity": 609.1409,
      "poster_path": "/kG3N8oQ10qiw2MsnSHFGJpQNyEy.jpg",
      "release_date": "2025-12-17",
      "title": "Avatar : De feu et de cendres",
      "video": false,
      "vote_average": 7.363,
      "vote_count": 2292
    },
    {
      "adult": false,
      "backdrop_path": "/kKF4gEiBDArhONlCcunHVgBp3bA.jpg",
      "genre_ids": [
        80,
        53
      ],
      "id": 1171145,
      "original_language": "en",
      "original_title": "Crime 101",
      "overview": "Dans Crime 101, les cambriolages méticuleux à LA le long de l'autoroute 101 d'un voleur de bijoux chevronné (Chris Hemsworth) déconcertent la police. Un flic solitaire (Mark Ruffalo) est à ses trousses. Lorsque leurs chemins croisent celui d'une courtière en assurance désabusée (Halle Berry), tous trois sont confrontés à des choix déterminants face aux millions de dollars en jeu.",
      "popularity": 338.7913,
      "poster_path": "/oUAbcXJXGMwX9sgUPf3Ljgob5jU.jpg",
      "release_date": "2026-02-11",
      "title": "Crime 101",
      "video": false,
      "vote_average": 7.025,
      "vote_count": 423
    },
    {
      "adult": false,
      "backdrop_path": "/uNToXatdunyvWXyXMrTI1nLvh6r.jpg",
      "genre_ids": [
        35,
        878,
        80
      ],
      "id": 1115544,
      "original_language": "en",
      "original_title": "Mike & Nick & Nick & Alice",
      "overview": "Deux gangsters et la femme qu'ils aiment tentent de survivre à la nuit la plus dangereuse de leur vie. Comme si cela ne suffisait pas, un élément imprévisible vient s'ajouter à l'équation : une machine à remonter le temps.",
      "popularity": 317.0002,
      "poster_path": "/fmimhXqKUmpwaOrYS2TAcEWvcMv.jpg",
      "release_date": "2026-03-14",
      "title": "Mike & Nick & Nick & Alice",
      "video": false,
      "vote_average": 6.797,
      "vote_count": 158
    },
    {
      "adult": false,
      "backdrop_path": "/nHxWyy18SvAZ8jJeemtS8k1UNjM.jpg",
      "genre_ids": [
        28,
        80,
        53
      ],
      "id": 1290821,
      "original_language": "en",
      "original_title": "Shelter",
      "overview": "Mason vit isolé sur une île écossaise. Après avoir sauvé une jeune fille de l'océan lors d'une terrible tempête, il déclenche une série d'événements qui provoquent une violente attaque dans son refuge...",
      "popularity": 324.5688,
      "poster_path": "/u071a2uGEgC5lAMskhxdASwfQSt.jpg",
      "release_date": "2026-01-28",
      "title": "Refuge Fatal",
      "video": false,
      "vote_average": 6.781,
      "vote_count": 474
    },
    {
      "adult": false,
      "backdrop_path": "/u53UYu5XG2hNgWGvs3xGhAVzypl.jpg",
      "genre_ids": [
        16,
        10751,
        878,
        12,
        35
      ],
      "id": 1327819,
      "original_language": "en",
      "original_title": "Hoppers",
      "overview": "Mabel est une jeune fille audacieuse qui a une grande ambition : infiltrer le monde animal. Pour ce faire, elle transfère son esprit à un robot castor afin de pouvoir approcher d’autres animaux et étudier leur mode de vie.",
      "popularity": 348.5408,
      "poster_path": "/tWmEsB3MtN7RfdXphzghC8B3ahX.jpg",
      "release_date": "2026-03-04",
      "title": "Jumpers",
      "video": false,
      "vote_average": 7.576,
      "vote_count": 386
    },
    {
      "adult": false,
      "backdrop_path": "/9Z2uDYXqJrlmePznQQJhL6d92Rq.jpg",
      "genre_ids": [
        16,
        12,
        14,
        10751,
        878
      ],
      "id": 1226863,
      "original_language": "en",
      "original_title": "The Super Mario Galaxy Movie",
      "overview": "Au-delà du Royaume Champignon, Mario, Luigi et Yoshi voyagent à travers les galaxies aux côtés de Rosalina pour arrêter Bowser Jr., dont la tentative de sauver son père menace l’équilibre de l’univers.",
      "popularity": 323.9395,
      "poster_path": "/aSQktALDmbunDbwkuZbZFMEWVFr.jpg",
      "release_date": "2026-04-01",
      "title": "Super Mario Galaxy, le film",
      "video": false,
      "vote_average": 6.9,
      "vote_count": 194
    },
    {
      "adult": false,
      "backdrop_path": "/tq3h43fZy0H80vzf47MAY7R9Mxo.jpg",
      "genre_ids": [
        16,
        35,
        10751
      ],
      "id": 1297842,
      "original_language": "en",
      "original_title": "GOAT",
      "overview": "Will est un petit bouc avec de grands rêves. Lorsqu'il décroche une chance inespérée de rejoindre la ligue professionnelle de \"roarball\", un sport ultra-intense réservé aux bêtes les plus rapides et féroces, il entend bien saisir l’opportunité. Problème : ses nouveaux coéquipiers ne sont pas vraiment ravis d'avoir un \"petit\" dans l'équipe. Mais Will est prêt à tout pour changer les règles du jeu.",
      "popularity": 280.7787,
      "poster_path": "/9wwbYnU3HfAYqdjbFMhy2a8HYvr.jpg",
      "release_date": "2026-02-11",
      "title": "GOAT : Rêver plus haut",
      "video": false,
      "vote_average": 7.875,
      "vote_count": 315
    },
    {
      "adult": false,
      "backdrop_path": "/z3bzhmC0CPikWeerUkLO73YvGrC.jpg",
      "genre_ids": [
        27,
        53,
        10402,
        28
      ],
      "id": 1084187,
      "original_language": "en",
      "original_title": "Pretty Lethal",
      "overview": "Un thriller effréné où cinq ballerines, bloquées dans une forêt isolée en chemin vers un concours de danse, se réfugient dans une sinistre auberge routière tenue par Devora Kasimer et doivent transformer leur formation d'élite pour survivre.",
      "popularity": 252.3131,
      "poster_path": "/xnh0rBBPKB6DyLiqek8dX1X7F7t.jpg",
      "release_date": "2026-03-13",
      "title": "Pirouette fatale",
      "video": false,
      "vote_average": 6.947,
      "vote_count": 206
    },
    {
      "adult": false,
      "backdrop_path": "/yWCZc2TcsCYbMMjvUIsczmQi2TX.jpg",
      "genre_ids": [
        27,
        9648,
        80
      ],
      "id": 1159559,
      "original_language": "en",
      "original_title": "Scream 7",
      "overview": "Lorsqu’un nouveau Ghostface surgit dans la paisible ville où Sidney Prescott a reconstruit sa vie, ses pires cauchemars refont surface. Alors que sa fille devient la prochaine cible, Sidney n’a d’autre choix que de reprendre le combat. Déterminée à protéger les siens, elle doit alors affronter les démons de son passé pour tenter de mettre fin une bonne fois pour toutes au bain de sang.",
      "popularity": 218.8374,
      "poster_path": "/j6Y7vqULt8tRlXVFXHK5aj3nCo4.jpg",
      "release_date": "2026-02-25",
      "title": "Scream 7",
      "video": false,
      "vote_average": 5.954,
      "vote_count": 620
    },
    {
      "adult": false,
      "backdrop_path": "/8Tfys3mDZVp4tNoH2ktm06a0Tau.jpg",
      "genre_ids": [
        878,
        12
      ],
      "id": 687163,
      "original_language": "en",
      "original_title": "Project Hail Mary",
      "overview": "Le professeur de sciences Ryland Grace se réveille à bord d’un vaisseau spatial, à des années-lumière de la Terre, sans aucun souvenir de qui il est ni de la façon dont il est arrivé là. À mesure que sa mémoire lui revient, il commence à découvrir sa mission : résoudre l’énigme d’une mystérieuse substance qui provoque l’extinction du Soleil. Il doit faire appel à ses connaissances scientifiques et ses idées peu orthodoxes pour sauver toute vie sur Terre mais une amitié inattendue pourrait signifier qu’il n’aura pas à accomplir cette tâche seul.",
      "popularity": 226.5197,
      "poster_path": "/wzyy8ZrsuHfAt4iz4iH3rT0tdoT.jpg",
      "release_date": "2026-03-15",
      "title": "Projet dernière chance",
      "video": false,
      "vote_average": 8.2,
      "vote_count": 989
    },
    {
      "adult": false,
      "backdrop_path": "/wns4x1GyxCudgOZRyhXKjXVJf3T.jpg",
      "genre_ids": [
        12,
        53,
        878
      ],
      "id": 840464,
      "original_language": "en",
      "original_title": "Greenland 2: Migration",
      "overview": "Après l'impact dévastateur d'une comète qui a réduit la Terre en ruines, la famille Garrity doit quitter la sécurité de son bunker au Groenland. Commence alors un périple pour leur survie et l'avenir de l'Humanité à travers un monde dévasté à la recherche d'un nouveau foyer.",
      "popularity": 228.3616,
      "poster_path": "/mu05wZK0MH2bYmuO7hXwZECqC1X.jpg",
      "release_date": "2026-01-07",
      "title": "Greenland : Migration",
      "video": false,
      "vote_average": 6.484,
      "vote_count": 805
    },
    {
      "adult": false,
      "backdrop_path": "/6yeVcxFR0j08vlv2OlL6zbewm4D.jpg",
      "genre_ids": [
        28,
        878,
        53
      ],
      "id": 1265609,
      "original_language": "en",
      "original_title": "War Machine",
      "overview": "Lors d'une dernière mission éprouvante pendant sa formation de Ranger, un ingénieur militaire doit mener son unité contre une gigantesque machine à tuer venue d'un autre monde.",
      "popularity": 210.4948,
      "poster_path": "/tlPgDzwIE7VYYIIAGCTUOnN4wI1.jpg",
      "release_date": "2026-02-12",
      "title": "War Machine",
      "video": false,
      "vote_average": 7.3,
      "vote_count": 1304
    },
    {
      "adult": false,
      "backdrop_path": "/5KFThZkdBEQkp9gPWWWNb5CI5yD.jpg",
      "genre_ids": [
        53,
        28,
        18
      ],
      "id": 1268127,
      "original_language": "ko",
      "original_title": "휴민트",
      "overview": "Zo In-sung et Park Jeong-min incarnent deux agents ennemis de Corée du Sud et du Nord qui risquent leur vie et leur loyauté pour se dévouer à une même cause : une informatrice.",
      "popularity": 214.8673,
      "poster_path": "/f7sCSLEPRfV2fWQ0RYOtHhnHXuG.jpg",
      "release_date": "2026-02-11",
      "title": "Humint",
      "video": false,
      "vote_average": 7.181,
      "vote_count": 36
    },
    {
      "adult": false,
      "backdrop_path": "/9n2tJBplPbgR2ca05hS5CKXwP2c.jpg",
      "genre_ids": [
        10751,
        35,
        12,
        16,
        14
      ],
      "id": 502356,
      "original_language": "en",
      "original_title": "The Super Mario Bros. Movie",
      "overview": "Alors qu’ils tentent de réparer une canalisation souterraine, Mario et son frère Luigi, tous deux plombiers, se retrouvent plongés dans un nouvel univers féerique à travers un mystérieux conduit. Mais lorsque les deux frères sont séparés, Mario s’engage dans une aventure trépidante pour retrouver Luigi. Dans sa quête, il peut compter sur l’aide du champignon Toad, habitant du Royaume Champignon, et les conseils avisés, en matière de techniques de combat, de la Princesse Peach, guerrière déterminée à la tête du Royaume. C’est ainsi que Mario réussit à mobiliser ses propres forces pour aller au bout de sa mission.",
      "popularity": 189.1951,
      "poster_path": "/ahMxyHMSJXingQr4yJBMzMU9k42.jpg",
      "release_date": "2023-04-05",
      "title": "Super Mario Bros., le film",
      "video": false,
      "vote_average": 7.587,
      "vote_count": 10412
    },
    {
      "adult": false,
      "backdrop_path": "/tZiRd4IpoNiaoLXr2o2YfhTMjE2.jpg",
      "genre_ids": [
        12,
        28
      ],
      "id": 662707,
      "original_language": "en",
      "original_title": "Starbright",
      "overview": "Aisling fait un vœu en voyant une étoile filante, un vœu qui pourrait bouleverser ou détruire sa vie. L’archange Raphaël apparaît, dissimule la lumière vivante de l’étoile dans son cœur, mais son pouvoir attire des poursuivants impitoyables. Joshua, un inconnu hanté, rejoint leur fuite et, ensemble, ils apprennent que le véritable don de l’étoile est le courage d’espérer, de pardonner et d’aimer.",
      "popularity": 173.1379,
      "poster_path": "/m1Zl07DNYeSyNcz9hf8hDsS2oB5.jpg",
      "release_date": "2026-02-27",
      "title": "Starbright",
      "video": false,
      "vote_average": 7.375,
      "vote_count": 8
    },
    {
      "adult": false,
      "backdrop_path": "/gCmfeKmEAZBP5gcXpiqb0gii9rS.jpg",
      "genre_ids": [
        27,
        53,
        35
      ],
      "id": 1198994,
      "original_language": "en",
      "original_title": "Send Help",
      "overview": "Après un terrible accident d'avion, deux collègues d'une compagnie se retrouvent seuls survivants, coincés sur une île déserte. L'une est une employée maligne et pleine de ressources, l'autre son patron tyrannique et désagréable. Obligés de s'adapter aux conditions extrêmes de leur isolement, ils doivent surmonter leurs vieilles rancunes et travailler ensemble pour survivre.",
      "popularity": 140.391,
      "poster_path": "/bMAn4qERdEfxotddEHWfMmkfjRv.jpg",
      "release_date": "2026-01-22",
      "title": "Send Help",
      "video": false,
      "vote_average": 7.079,
      "vote_count": 825
    },
    {
      "adult": false,
      "backdrop_path": "/61RYedFgX1K07xgVIvdJzukSR4g.jpg",
      "genre_ids": [
        35,
        18,
        10751,
        10749
      ],
      "id": 848116,
      "original_language": "hi",
      "original_title": "रॉकी और रानी की प्रेम कहानी",
      "overview": "Rocky, un mordu de gymnastique, tombe amoureux de Rani, qui vient d'une famille bengalie bien éduquée. Comme ils appartiennent à des mondes diamétralement opposés, ils décident d'échanger leurs familles pour s'adapter à la culture et au milieu de chacun et pour savoir si leur mariage survivra. Rocky et Rani sont piégés dans un monde où ils sont unis par l'amour mais divisés par leurs familles, et la question ultime est de savoir s'ils y trouveront leur place.",
      "popularity": 150.2287,
      "poster_path": "/vTQIqlxUkOuyf2UKhlM2OUaFGKz.jpg",
      "release_date": "2023-07-28",
      "title": "रॉकी और रानी की प्रेम कहानी",
      "video": false,
      "vote_average": 6.045,
      "vote_count": 78
    },
    {
      "adult": false,
      "backdrop_path": "/lgotja3xMoJZbynwHfcQcJAEMWH.jpg",
      "genre_ids": [
        16,
        10751,
        9648,
        12,
        35
      ],
      "id": 1084242,
      "original_language": "en",
      "original_title": "Zootopia 2",
      "overview": "Judy Hopps et Nick Wilde explorent à nouveau Zootopie, entre mystères, rires et rencontres inattendues. À travers chaque rue et chaque instant, ils découvrent que l’amitié et la curiosité transforment le quotidien en moments magiques.",
      "popularity": 140.8484,
      "poster_path": "/hBI7Wrps6tDjhEzBxJgoPLhbmT1.jpg",
      "release_date": "2025-11-26",
      "title": "Zootopie 2",
      "video": false,
      "vote_average": 7.597,
      "vote_count": 2457
    },
    {
      "adult": false,
      "backdrop_path": "/4840rkbpsiuow5ew155oVKcqJwj.jpg",
      "genre_ids": [
        18
      ],
      "id": 615,
      "original_language": "en",
      "original_title": "The Passion of the Christ",
      "overview": "Les douze dernières heures de la vie du Christ. Rendu au Mont des Oliviers, Jésus prie après avoir partagé un dernier repas avec ses apôtres. Il résiste maintenant aux tentations de Satan. Trahi par Judas, Jésus est arrêté et emmené à Jérusalem, où les chefs des Pharisiens l'accusent de blasphème et lui font un procès qui a pour issue sa condamnation à mort…",
      "popularity": 157.6868,
      "poster_path": "/nVjopQNIWFGQ4Kk73QxAeIw6xov.jpg",
      "release_date": "2004-02-25",
      "title": "La Passion du Christ",
      "video": false,
      "vote_average": 7.534,
      "vote_count": 5115
    }
  ],
  "total_pages": 55991,
  "total_results": 1119805
}